Metadata-Version: 2.1
Name: pipy_test_123456
Version: 0.1.0
Summary: test pip upload
Home-page: 
Author: xp
Author-email: 1426813058@qq.com
License: MIT
